setup.py
matrix_oprs/__init__.py
matrix_oprs/matrix_calc.py
matrix_oprs.egg-info/PKG-INFO
matrix_oprs.egg-info/SOURCES.txt
matrix_oprs.egg-info/dependency_links.txt
matrix_oprs.egg-info/not-zip-safe
matrix_oprs.egg-info/top_level.txt