Metadata-Version: 1.0
Name: matrix-oprs
Version: 1.2
Summary: matrix additon and multiplication
Home-page: UNKNOWN
Author: Rasmi KR
Author-email: rasmikr41@gmail.com
License: UNKNOWN
Platform: UNKNOWN
